autoocr/__init__.py
autoocr/autoocr.py
autoocr/config.json
autoocr/lang_map.json
autoocr-0.0.3.dist-info/LICENSE
autoocr-0.0.3.dist-info/METADATA
autoocr-0.0.3.dist-info/WHEEL
autoocr-0.0.3.dist-info/top_level.txt
autoocr-0.0.3.dist-info/RECORD
