Metadata-Version: 2.1
Name: autoocr
Version: 0.0.3
Summary: A Python wrapper for cross platform tesseract OCR engine with multiple languages (e.g. Bangla)
Home-page: https://github.com/zabir-nabil/autoocr
Author: Zabir Al Nazi Nabil
Author-email: zabiralnazi@yahoo.com
License: MIT
Keywords: ocr
Platform: UNKNOWN
